lfsr.v
module LFSR #(parameter N = 32)(clk,seed,rst_n,out);
    input rst_n,clk;
    input [N-1:0] seed;
    output [N-1:0] out;

    reg [N-1:0] r;

    // tap seaqunce is [32,3,2,0]

    always @(posedge clk) begin
        if (rst_n) begin
            r <= seed;
        end else begin
            //r <= (r<<1) | (r[31]^r[2]^r[1]^1'b1);
            r <= (r<<1) | (r[7]^r[5]^r[4]^r[3]^1'b1);
        end
    end
    assign out = r;
endmodule

module comparator #(parameter N=8) (input [N-1:0] t, input [N-1:0] rnd, output ber);
    wire [N:0] tmp;
    wire [N:0] rnd_c;
    wire [N:0] rnd_ext;
    wire [N:0] t_ext;

    // 符号拡張 必ず0
    assign rnd_ext={1'b0,rnd};
    assign rnd_c = ~rnd_ext+1'b1;
    // 符号拡張　必ず0
    assign t_ext = {1'b0,t};
    assign tmp = t_ext + rnd_c;
    // 最上位ビットが比較の情報
    assign ber = ~tmp[N];
endmodule

`timescale 1ps/1ps

module LFSR_tb;
    parameter M=8;
    reg clk;
    reg [M-1:0] seed;
    reg rst_n;
    wire [M-1:0] out;

    reg [M-1:0] target;
    wire ber_out;

    LFSR #(.N(M)) LFSR(clk,seed,rst_n,out);
    comparator #(.N(M)) comparator(target,out,ber_out);

    parameter P_CLOCK_FREQ = 1000.0 / 50.0;//50MHz

    integer fd;

    initial begin
        $dumpfile("lfsr.vcd");
        //dumpvars にtopmodule のインスタンス名を載せないと波形の中身は見れない。
        $dumpvars(0,LFSR,comparator);
        $monitor("%t: clk = %b, seed = %b, rst_n = %b, out= %b",$time,clk,seed,rst_n,out);
        fd = $fopen("output_data.txt","w");
        $display(fd,"%b",clk);

        clk <= 1'b0;
        rst_n <=1;
        seed <=1;
        target <= 85;
        #2
        rst_n<=0;
        #509
        $finish;
        $fclose(fd);
    end
    //always #(P_CLOCK_FREQ/2) begin
    always #1 begin
        clk <= ~clk;
        $fwrite(fd,"%b\n",ber_out);
    end
endmodule

lfsr.vcd
$date
	Sun Sep 18 22:19:22 2022
$end
$version
	Icarus Verilog
$end
$timescale
	1ps
$end
$scope module LFSR_tb $end
$scope module LFSR $end
$var wire 1 ! clk $end
$var wire 1 " rst_n $end
$var wire 8 # seed [7:0] $end
$var wire 8 $ out [7:0] $end
$var reg 9 % r [8:0] $end
$upscope $end
$upscope $end
$scope module LFSR_tb $end
$scope module comparator $end
$var wire 1 & ber $end
$var wire 8 ' rnd [7:0] $end
$var wire 8 ( t [7:0] $end
$var wire 9 ) tmp [8:0] $end
$var wire 9 * t_ext [8:0] $end
$var wire 9 + rnd_ext [8:0] $end
$var wire 9 , rnd_c [8:0] $end
$upscope $end
$upscope $end
$enddefinitions $end
#0
$dumpvars
bx ,
b0xxxxxxxx +
b1010101 *
bx )
b1010101 (
bx '
x&
bx %
bx $
b1 #
1"
0!
$end
#1
1&
b1010100 )
b111111111 ,
b1 +
b1 $
b1 '
b1 %
1!
#2
0!
0"
#3
b1010010 )
b111111101 ,
b11 +
b11 $
b11 '
b11 %
1!
#4
0!
#5
b1001110 )
b111111001 ,
b111 +
b111 $
b111 '
b111 %
1!
#6
0!
#7
b1000110 )
b111110001 ,
b1111 +
b1111 $
b1111 '
b1111 %
1!
#8
0!
#9
b110111 )
b111100010 ,
b11110 +
b11110 $
b11110 '
b11110 %
1!
#10
0!
#11
b11000 )
b111000011 ,
b111101 +
b111101 $
b111101 '
b111101 %
1!
#12
0!
#13
0&
b111011011 )
b110000110 ,
b1111010 +
b1111010 $
b1111010 '
b1111010 %
1!
#14
0!
#15
b101100001 )
b100001100 ,
b11110100 +
b11110100 $
b11110100 '
b11110100 %
1!
#16
0!
#17
b101101101 )
b100011000 ,
b11101000 +
b11101000 $
b11101000 '
b111101000 %
1!
#18
0!
#19
b110000101 )
b100110000 ,
b11010000 +
b11010000 $
b11010000 '
b111010000 %
1!
#20
0!
#21
b110110100 )
b101011111 ,
b10100001 +
b10100001 $
b10100001 '
b110100001 %
1!
#22
0!
#23
1&
b10010 )
b110111101 ,
b1000011 +
b1000011 $
b1000011 '
b101000011 %
1!
#24
0!
#25
0&
b111001110 )
b101111001 ,
b10000111 +
b10000111 $
b10000111 '
b10000111 %
1!
#26
0!
#27
1&
b1000111 )
b111110010 ,
b1110 +
b1110 $
b1110 '
b100001110 %
1!
#28
0!
#29
b111001 )
b111100100 ,
b11100 +
b11100 $
b11100 '
b11100 %
1!
#30
0!
#31
b11100 )
b111000111 ,
b111001 +
b111001 $
b111001 '
b111001 %
1!
#32
0!
#33
0&
b111100011 )
b110001110 ,
b1110010 +
b1110010 $
b1110010 '
b1110010 %
1!
#34
0!
#35
b101110000 )
b100011011 ,
b11100101 +
b11100101 $
b11100101 '
b11100101 %
1!
#36
0!
#37
b110001010 )
b100110101 ,
b11001011 +
b11001011 $
b11001011 '
b111001011 %
1!
#38
0!
#39
b110111110 )
b101101001 ,
b10010111 +
b10010111 $
b10010111 '
b110010111 %
1!
#40
0!
#41
1&
b100110 )
b111010001 ,
b101111 +
b101111 $
b101111 '
b100101111 %
1!
#42
0!
#43
0&
b111110110 )
b110100001 ,
b1011111 +
b1011111 $
b1011111 '
b1011111 %
1!
#44
0!
#45
b110010110 )
b101000001 ,
b10111111 +
b10111111 $
b10111111 '
b10111111 %
1!
#46
0!
#47
b111010110 )
b110000001 ,
b1111111 +
b1111111 $
b1111111 '
b101111111 %
1!
#48
0!
#49
b101010111 )
b100000010 ,
b11111110 +
b11111110 $
b11111110 '
b11111110 %
1!
#50
0!
#51
b101011000 )
b100000011 ,
b11111101 +
b11111101 $
b11111101 '
b111111101 %
1!
#52
0!
#53
b101011010 )
b100000101 ,
b11111011 +
b11111011 $
b11111011 '
b111111011 %
1!
#54
0!
#55
b101011110 )
b100001001 ,
b11110111 +
b11110111 $
b11110111 '
b111110111 %
1!
#56
0!
#57
b101100111 )
b100010010 ,
b11101110 +
b11101110 $
b11101110 '
b111101110 %
1!
#58
0!
#59
b101111001 )
b100100100 ,
b11011100 +
b11011100 $
b11011100 '
b111011100 %
1!
#60
0!
#61
b110011101 )
b101001000 ,
b10111000 +
b10111000 $
b10111000 '
b110111000 %
1!
#62
0!
#63
b111100100 )
b110001111 ,
b1110001 +
b1110001 $
b1110001 '
b101110001 %
1!
#64
0!
#65
b101110010 )
b100011101 ,
b11100011 +
b11100011 $
b11100011 '
b11100011 %
1!
#66
0!
#67
b110001110 )
b100111001 ,
b11000111 +
b11000111 $
b11000111 '
b111000111 %
1!
#68
0!
#69
b111000111 )
b101110010 ,
b10001110 +
b10001110 $
b10001110 '
b110001110 %
1!
#70
0!
#71
1&
b111000 )
b111100011 ,
b11101 +
b11101 $
b11101 '
b100011101 %
1!
#72
0!
#73
b11010 )
b111000101 ,
b111011 +
b111011 $
b111011 '
b111011 %
1!
#74
0!
#75
0&
b111011111 )
b110001010 ,
b1110110 +
b1110110 $
b1110110 '
b1110110 %
1!
#76
0!
#77
b101101000 )
b100010011 ,
b11101101 +
b11101101 $
b11101101 '
b11101101 %
1!
#78
0!
#79
b101111011 )
b100100110 ,
b11011010 +
b11011010 $
b11011010 '
b111011010 %
1!
#80
0!
#81
b110100001 )
b101001100 ,
b10110100 +
b10110100 $
b10110100 '
b110110100 %
1!
#82
0!
#83
b111101101 )
b110011000 ,
b1101000 +
b1101000 $
b1101000 '
b101101000 %
1!
#84
0!
#85
b110000100 )
b100101111 ,
b11010001 +
b11010001 $
b11010001 '
b11010001 %
1!
#86
0!
#87
b110110010 )
b101011101 ,
b10100011 +
b10100011 $
b10100011 '
b110100011 %
1!
#88
0!
#89
1&
b1110 )
b110111001 ,
b1000111 +
b1000111 $
b1000111 '
b101000111 %
1!
#90
0!
#91
0&
b111000110 )
b101110001 ,
b10001111 +
b10001111 $
b10001111 '
b10001111 %
1!
#92
0!
#93
1&
b110110 )
b111100001 ,
b11111 +
b11111 $
b11111 '
b100011111 %
1!
#94
0!
#95
b10110 )
b111000001 ,
b111111 +
b111111 $
b111111 '
b111111 %
1!
#96
0!
#97
0&
b111010111 )
b110000010 ,
b1111110 +
b1111110 $
b1111110 '
b1111110 %
1!
#98
0!
#99
b101011001 )
b100000100 ,
b11111100 +
b11111100 $
b11111100 '
b11111100 %
1!
#100
0!
#101
b101011100 )
b100000111 ,
b11111001 +
b11111001 $
b11111001 '
b111111001 %
1!
#102
0!
#103
b101100010 )
b100001101 ,
b11110011 +
b11110011 $
b11110011 '
b111110011 %
1!
#104
0!
#105
b101101111 )
b100011010 ,
b11100110 +
b11100110 $
b11100110 '
b111100110 %
1!
#106
0!
#107
b110001000 )
b100110011 ,
b11001101 +
b11001101 $
b11001101 '
b111001101 %
1!
#108
0!
#109
b110111010 )
b101100101 ,
b10011011 +
b10011011 $
b10011011 '
b110011011 %
1!
#110
0!
#111
1&
b11111 )
b111001010 ,
b110110 +
b110110 $
b110110 '
b100110110 %
1!
#112
0!
#113
0&
b111101000 )
b110010011 ,
b1101101 +
b1101101 $
b1101101 '
b1101101 %
1!
#114
0!
#115
b101111010 )
b100100101 ,
b11011011 +
b11011011 $
b11011011 '
b11011011 %
1!
#116
0!
#117
b110011111 )
b101001010 ,
b10110110 +
b10110110 $
b10110110 '
b110110110 %
1!
#118
0!
#119
b111101001 )
b110010100 ,
b1101100 +
b1101100 $
b1101100 '
b101101100 %
1!
#120
0!
#121
b101111100 )
b100100111 ,
b11011001 +
b11011001 $
b11011001 '
b11011001 %
1!
#122
0!
#123
b110100011 )
b101001110 ,
b10110010 +
b10110010 $
b10110010 '
b110110010 %
1!
#124
0!
#125
b111110001 )
b110011100 ,
b1100100 +
b1100100 $
b1100100 '
b101100100 %
1!
#126
0!
#127
b110001101 )
b100111000 ,
b11001000 +
b11001000 $
b11001000 '
b11001000 %
1!
#128
0!
#129
b111000100 )
b101101111 ,
b10010001 +
b10010001 $
b10010001 '
b110010001 %
1!
#130
0!
#131
1&
b110010 )
b111011101 ,
b100011 +
b100011 $
b100011 '
b100100011 %
1!
#132
0!
#133
b1111 )
b110111010 ,
b1000110 +
b1000110 $
b1000110 '
b1000110 %
1!
#134
0!
#135
0&
b111001000 )
b101110011 ,
b10001101 +
b10001101 $
b10001101 '
b10001101 %
1!
#136
0!
#137
1&
b111010 )
b111100101 ,
b11011 +
b11011 $
b11011 '
b100011011 %
1!
#138
0!
#139
b11110 )
b111001001 ,
b110111 +
b110111 $
b110111 '
b110111 %
1!
#140
0!
#141
0&
b111100110 )
b110010001 ,
b1101111 +
b1101111 $
b1101111 '
b1101111 %
1!
#142
0!
#143
b101110110 )
b100100001 ,
b11011111 +
b11011111 $
b11011111 '
b11011111 %
1!
#144
0!
#145
b110010111 )
b101000010 ,
b10111110 +
b10111110 $
b10111110 '
b110111110 %
1!
#146
0!
#147
b111011000 )
b110000011 ,
b1111101 +
b1111101 $
b1111101 '
b101111101 %
1!
#148
0!
#149
b101011011 )
b100000110 ,
b11111010 +
b11111010 $
b11111010 '
b11111010 %
1!
#150
0!
#151
b101100000 )
b100001011 ,
b11110101 +
b11110101 $
b11110101 '
b111110101 %
1!
#152
0!
#153
b101101011 )
b100010110 ,
b11101010 +
b11101010 $
b11101010 '
b111101010 %
1!
#154
0!
#155
b110000001 )
b100101100 ,
b11010100 +
b11010100 $
b11010100 '
b111010100 %
1!
#156
0!
#157
b110101100 )
b101010111 ,
b10101001 +
b10101001 $
b10101001 '
b110101001 %
1!
#158
0!
#159
1&
b11 )
b110101110 ,
b1010010 +
b1010010 $
b1010010 '
b101010010 %
1!
#160
0!
#161
0&
b110110001 )
b101011100 ,
b10100100 +
b10100100 $
b10100100 '
b10100100 %
1!
#162
0!
#163
1&
b1100 )
b110110111 ,
b1001001 +
b1001001 $
b1001001 '
b101001001 %
1!
#164
0!
#165
0&
b111000011 )
b101101110 ,
b10010010 +
b10010010 $
b10010010 '
b10010010 %
1!
#166
0!
#167
1&
b110000 )
b111011011 ,
b100101 +
b100101 $
b100101 '
b100100101 %
1!
#168
0!
#169
b1011 )
b110110110 ,
b1001010 +
b1001010 $
b1001010 '
b1001010 %
1!
#170
0!
#171
0&
b111000001 )
b101101100 ,
b10010100 +
b10010100 $
b10010100 '
b10010100 %
1!
#172
0!
#173
1&
b101100 )
b111010111 ,
b101001 +
b101001 $
b101001 '
b100101001 %
1!
#174
0!
#175
b10 )
b110101101 ,
b1010011 +
b1010011 $
b1010011 '
b1010011 %
1!
#176
0!
#177
0&
b110101111 )
b101011010 ,
b10100110 +
b10100110 $
b10100110 '
b10100110 %
1!
#178
0!
#179
1&
b1000 )
b110110011 ,
b1001101 +
b1001101 $
b1001101 '
b101001101 %
1!
#180
0!
#181
0&
b110111011 )
b101100110 ,
b10011010 +
b10011010 $
b10011010 '
b10011010 %
1!
#182
0!
#183
1&
b100001 )
b111001100 ,
b110100 +
b110100 $
b110100 '
b100110100 %
1!
#184
0!
#185
0&
b111101100 )
b110010111 ,
b1101001 +
b1101001 $
b1101001 '
b1101001 %
1!
#186
0!
#187
b110000010 )
b100101101 ,
b11010011 +
b11010011 $
b11010011 '
b11010011 %
1!
#188
0!
#189
b110101110 )
b101011001 ,
b10100111 +
b10100111 $
b10100111 '
b110100111 %
1!
#190
0!
#191
1&
b110 )
b110110001 ,
b1001111 +
b1001111 $
b1001111 '
b101001111 %
1!
#192
0!
#193
0&
b110110111 )
b101100010 ,
b10011110 +
b10011110 $
b10011110 '
b10011110 %
1!
#194
0!
#195
1&
b11001 )
b111000100 ,
b111100 +
b111100 $
b111100 '
b100111100 %
1!
#196
0!
#197
0&
b111011101 )
b110001000 ,
b1111000 +
b1111000 $
b1111000 '
b1111000 %
1!
#198
0!
#199
b101100101 )
b100010000 ,
b11110000 +
b11110000 $
b11110000 '
b11110000 %
1!
#200
0!
#201
b101110101 )
b100100000 ,
b11100000 +
b11100000 $
b11100000 '
b111100000 %
1!
#202
0!
#203
b110010100 )
b100111111 ,
b11000001 +
b11000001 $
b11000001 '
b111000001 %
1!
#204
0!
#205
b111010011 )
b101111110 ,
b10000010 +
b10000010 $
b10000010 '
b110000010 %
1!
#206
0!
#207
1&
b1010001 )
b111111100 ,
b100 +
b100 $
b100 '
b100000100 %
1!
#208
0!
#209
b1001100 )
b111110111 ,
b1001 +
b1001 $
b1001 '
b1001 %
1!
#210
0!
#211
b1000011 )
b111101110 ,
b10010 +
b10010 $
b10010 '
b10010 %
1!
#212
0!
#213
b110001 )
b111011100 ,
b100100 +
b100100 $
b100100 '
b100100 %
1!
#214
0!
#215
b1101 )
b110111000 ,
b1001000 +
b1001000 $
b1001000 '
b1001000 %
1!
#216
0!
#217
0&
b111000101 )
b101110000 ,
b10010000 +
b10010000 $
b10010000 '
b10010000 %
1!
#218
0!
#219
1&
b110100 )
b111011111 ,
b100001 +
b100001 $
b100001 '
b100100001 %
1!
#220
0!
#221
b10011 )
b110111110 ,
b1000010 +
b1000010 $
b1000010 '
b1000010 %
1!
#222
0!
#223
0&
b111010000 )
b101111011 ,
b10000101 +
b10000101 $
b10000101 '
b10000101 %
1!
#224
0!
#225
1&
b1001011 )
b111110110 ,
b1010 +
b1010 $
b1010 '
b100001010 %
1!
#226
0!
#227
b1000001 )
b111101100 ,
b10100 +
b10100 $
b10100 '
b10100 %
1!
#228
0!
#229
b101101 )
b111011000 ,
b101000 +
b101000 $
b101000 '
b101000 %
1!
#230
0!
#231
b100 )
b110101111 ,
b1010001 +
b1010001 $
b1010001 '
b1010001 %
1!
#232
0!
#233
0&
b110110011 )
b101011110 ,
b10100010 +
b10100010 $
b10100010 '
b10100010 %
1!
#234
0!
#235
1&
b10000 )
b110111011 ,
b1000101 +
b1000101 $
b1000101 '
b101000101 %
1!
#236
0!
#237
0&
b111001010 )
b101110101 ,
b10001011 +
b10001011 $
b10001011 '
b10001011 %
1!
#238
0!
#239
1&
b111110 )
b111101001 ,
b10111 +
b10111 $
b10111 '
b100010111 %
1!
#240
0!
#241
b100111 )
b111010010 ,
b101110 +
b101110 $
b101110 '
b101110 %
1!
#242
0!
#243
0&
b111111000 )
b110100011 ,
b1011101 +
b1011101 $
b1011101 '
b1011101 %
1!
#244
0!
#245
b110011010 )
b101000101 ,
b10111011 +
b10111011 $
b10111011 '
b10111011 %
1!
#246
0!
#247
b111011110 )
b110001001 ,
b1110111 +
b1110111 $
b1110111 '
b101110111 %
1!
#248
0!
#249
b101100110 )
b100010001 ,
b11101111 +
b11101111 $
b11101111 '
b11101111 %
1!
#250
0!
#251
b101110111 )
b100100010 ,
b11011110 +
b11011110 $
b11011110 '
b111011110 %
1!
#252
0!
#253
b110011001 )
b101000100 ,
b10111100 +
b10111100 $
b10111100 '
b110111100 %
1!
#254
0!
#255
b111011100 )
b110000111 ,
b1111001 +
b1111001 $
b1111001 '
b101111001 %
1!
#256
0!
#257
b101100011 )
b100001110 ,
b11110010 +
b11110010 $
b11110010 '
b11110010 %
1!
#258
0!
#259
b101110001 )
b100011100 ,
b11100100 +
b11100100 $
b11100100 '
b111100100 %
1!
#260
0!
#261
b110001100 )
b100110111 ,
b11001001 +
b11001001 $
b11001001 '
b111001001 %
1!
#262
0!
#263
b111000010 )
b101101101 ,
b10010011 +
b10010011 $
b10010011 '
b110010011 %
1!
#264
0!
#265
1&
b101110 )
b111011001 ,
b100111 +
b100111 $
b100111 '
b100100111 %
1!
#266
0!
#267
b111 )
b110110010 ,
b1001110 +
b1001110 $
b1001110 '
b1001110 %
1!
#268
0!
#269
0&
b110111001 )
b101100100 ,
b10011100 +
b10011100 $
b10011100 '
b10011100 %
1!
#270
0!
#271
1&
b11101 )
b111001000 ,
b111000 +
b111000 $
b111000 '
b100111000 %
1!
#272
0!
#273
0&
b111100101 )
b110010000 ,
b1110000 +
b1110000 $
b1110000 '
b1110000 %
1!
#274
0!
#275
b101110100 )
b100011111 ,
b11100001 +
b11100001 $
b11100001 '
b11100001 %
1!
#276
0!
#277
b110010010 )
b100111101 ,
b11000011 +
b11000011 $
b11000011 '
b111000011 %
1!
#278
0!
#279
b111001111 )
b101111010 ,
b10000110 +
b10000110 $
b10000110 '
b110000110 %
1!
#280
0!
#281
1&
b1001001 )
b111110100 ,
b1100 +
b1100 $
b1100 '
b100001100 %
1!
#282
0!
#283
b111101 )
b111101000 ,
b11000 +
b11000 $
b11000 '
b11000 %
1!
#284
0!
#285
b100100 )
b111001111 ,
b110001 +
b110001 $
b110001 '
b110001 %
1!
#286
0!
#287
0&
b111110010 )
b110011101 ,
b1100011 +
b1100011 $
b1100011 '
b1100011 %
1!
#288
0!
#289
b110001111 )
b100111010 ,
b11000110 +
b11000110 $
b11000110 '
b11000110 %
1!
#290
0!
#291
b111001001 )
b101110100 ,
b10001100 +
b10001100 $
b10001100 '
b110001100 %
1!
#292
0!
#293
1&
b111100 )
b111100111 ,
b11001 +
b11001 $
b11001 '
b100011001 %
1!
#294
0!
#295
b100010 )
b111001101 ,
b110011 +
b110011 $
b110011 '
b110011 %
1!
#296
0!
#297
0&
b111101110 )
b110011001 ,
b1100111 +
b1100111 $
b1100111 '
b1100111 %
1!
#298
0!
#299
b110000111 )
b100110010 ,
b11001110 +
b11001110 $
b11001110 '
b11001110 %
1!
#300
0!
#301
b110111000 )
b101100011 ,
b10011101 +
b10011101 $
b10011101 '
b110011101 %
1!
#302
0!
#303
1&
b11011 )
b111000110 ,
b111010 +
b111010 $
b111010 '
b100111010 %
1!
#304
0!
#305
0&
b111100001 )
b110001100 ,
b1110100 +
b1110100 $
b1110100 '
b1110100 %
1!
#306
0!
#307
b101101100 )
b100010111 ,
b11101001 +
b11101001 $
b11101001 '
b11101001 %
1!
#308
0!
#309
b110000011 )
b100101110 ,
b11010010 +
b11010010 $
b11010010 '
b111010010 %
1!
#310
0!
#311
b110110000 )
b101011011 ,
b10100101 +
b10100101 $
b10100101 '
b110100101 %
1!
#312
0!
#313
1&
b1010 )
b110110101 ,
b1001011 +
b1001011 $
b1001011 '
b101001011 %
1!
#314
0!
#315
0&
b110111111 )
b101101010 ,
b10010110 +
b10010110 $
b10010110 '
b10010110 %
1!
#316
0!
#317
1&
b101000 )
b111010011 ,
b101101 +
b101101 $
b101101 '
b100101101 %
1!
#318
0!
#319
0&
b111111010 )
b110100101 ,
b1011011 +
b1011011 $
b1011011 '
b1011011 %
1!
#320
0!
#321
b110011110 )
b101001001 ,
b10110111 +
b10110111 $
b10110111 '
b10110111 %
1!
#322
0!
#323
b111100111 )
b110010010 ,
b1101110 +
b1101110 $
b1101110 '
b101101110 %
1!
#324
0!
#325
b101111000 )
b100100011 ,
b11011101 +
b11011101 $
b11011101 '
b11011101 %
1!
#326
0!
#327
b110011011 )
b101000110 ,
b10111010 +
b10111010 $
b10111010 '
b110111010 %
1!
#328
0!
#329
b111100000 )
b110001011 ,
b1110101 +
b1110101 $
b1110101 '
b101110101 %
1!
#330
0!
#331
b101101010 )
b100010101 ,
b11101011 +
b11101011 $
b11101011 '
b11101011 %
1!
#332
0!
#333
b101111111 )
b100101010 ,
b11010110 +
b11010110 $
b11010110 '
b111010110 %
1!
#334
0!
#335
b110101000 )
b101010011 ,
b10101101 +
b10101101 $
b10101101 '
b110101101 %
1!
#336
0!
#337
b111111011 )
b110100110 ,
b1011010 +
b1011010 $
b1011010 '
b101011010 %
1!
#338
0!
#339
b110100000 )
b101001011 ,
b10110101 +
b10110101 $
b10110101 '
b10110101 %
1!
#340
0!
#341
b111101011 )
b110010110 ,
b1101010 +
b1101010 $
b1101010 '
b101101010 %
1!
#342
0!
#343
b110000000 )
b100101011 ,
b11010101 +
b11010101 $
b11010101 '
b11010101 %
1!
#344
0!
#345
b110101010 )
b101010101 ,
b10101011 +
b10101011 $
b10101011 '
b110101011 %
1!
#346
0!
#347
b111111111 )
b110101010 ,
b1010110 +
b1010110 $
b1010110 '
b101010110 %
1!
#348
0!
#349
b110101001 )
b101010100 ,
b10101100 +
b10101100 $
b10101100 '
b10101100 %
1!
#350
0!
#351
b111111101 )
b110101000 ,
b1011000 +
b1011000 $
b1011000 '
b101011000 %
1!
#352
0!
#353
b110100100 )
b101001111 ,
b10110001 +
b10110001 $
b10110001 '
b10110001 %
1!
#354
0!
#355
b111110011 )
b110011110 ,
b1100010 +
b1100010 $
b1100010 '
b101100010 %
1!
#356
0!
#357
b110010001 )
b100111100 ,
b11000100 +
b11000100 $
b11000100 '
b11000100 %
1!
#358
0!
#359
b111001101 )
b101111000 ,
b10001000 +
b10001000 $
b10001000 '
b110001000 %
1!
#360
0!
#361
1&
b1000100 )
b111101111 ,
b10001 +
b10001 $
b10001 '
b100010001 %
1!
#362
0!
#363
b110011 )
b111011110 ,
b100010 +
b100010 $
b100010 '
b100010 %
1!
#364
0!
#365
b10001 )
b110111100 ,
b1000100 +
b1000100 $
b1000100 '
b1000100 %
1!
#366
0!
#367
0&
b111001100 )
b101110111 ,
b10001001 +
b10001001 $
b10001001 '
b10001001 %
1!
#368
0!
#369
1&
b1000010 )
b111101101 ,
b10011 +
b10011 $
b10011 '
b100010011 %
1!
#370
0!
#371
b101111 )
b111011010 ,
b100110 +
b100110 $
b100110 '
b100110 %
1!
#372
0!
#373
b1001 )
b110110100 ,
b1001100 +
b1001100 $
b1001100 '
b1001100 %
1!
#374
0!
#375
0&
b110111101 )
b101101000 ,
b10011000 +
b10011000 $
b10011000 '
b10011000 %
1!
#376
0!
#377
1&
b100101 )
b111010000 ,
b110000 +
b110000 $
b110000 '
b100110000 %
1!
#378
0!
#379
0&
b111110100 )
b110011111 ,
b1100001 +
b1100001 $
b1100001 '
b1100001 %
1!
#380
0!
#381
b110010011 )
b100111110 ,
b11000010 +
b11000010 $
b11000010 '
b11000010 %
1!
#382
0!
#383
b111010001 )
b101111100 ,
b10000100 +
b10000100 $
b10000100 '
b110000100 %
1!
#384
0!
#385
1&
b1001101 )
b111111000 ,
b1000 +
b1000 $
b1000 '
b100001000 %
1!
#386
0!
#387
b1000101 )
b111110000 ,
b10000 +
b10000 $
b10000 '
b10000 %
1!
#388
0!
#389
b110101 )
b111100000 ,
b100000 +
b100000 $
b100000 '
b100000 %
1!
#390
0!
#391
b10101 )
b111000000 ,
b1000000 +
b1000000 $
b1000000 '
b1000000 %
1!
#392
0!
#393
0&
b111010100 )
b101111111 ,
b10000001 +
b10000001 $
b10000001 '
b10000001 %
1!
#394
0!
#395
1&
b1010011 )
b111111110 ,
b10 +
b10 $
b10 '
b100000010 %
1!
#396
0!
#397
b1010000 )
b111111011 ,
b101 +
b101 $
b101 '
b101 %
1!
#398
0!
#399
b1001010 )
b111110101 ,
b1011 +
b1011 $
b1011 '
b1011 %
1!
#400
0!
#401
b111111 )
b111101010 ,
b10110 +
b10110 $
b10110 '
b10110 %
1!
#402
0!
#403
b101001 )
b111010100 ,
b101100 +
b101100 $
b101100 '
b101100 %
1!
#404
0!
#405
0&
b111111100 )
b110100111 ,
b1011001 +
b1011001 $
b1011001 '
b1011001 %
1!
#406
0!
#407
b110100010 )
b101001101 ,
b10110011 +
b10110011 $
b10110011 '
b10110011 %
1!
#408
0!
#409
b111101111 )
b110011010 ,
b1100110 +
b1100110 $
b1100110 '
b101100110 %
1!
#410
0!
#411
b110001001 )
b100110100 ,
b11001100 +
b11001100 $
b11001100 '
b11001100 %
1!
#412
0!
#413
b110111100 )
b101100111 ,
b10011001 +
b10011001 $
b10011001 '
b110011001 %
1!
#414
0!
#415
1&
b100011 )
b111001110 ,
b110010 +
b110010 $
b110010 '
b100110010 %
1!
#416
0!
#417
0&
b111110000 )
b110011011 ,
b1100101 +
b1100101 $
b1100101 '
b1100101 %
1!
#418
0!
#419
b110001011 )
b100110110 ,
b11001010 +
b11001010 $
b11001010 '
b11001010 %
1!
#420
0!
#421
b111000000 )
b101101011 ,
b10010101 +
b10010101 $
b10010101 '
b110010101 %
1!
#422
0!
#423
1&
b101010 )
b111010101 ,
b101011 +
b101011 $
b101011 '
b100101011 %
1!
#424
0!
#425
0&
b111111110 )
b110101001 ,
b1010111 +
b1010111 $
b1010111 '
b1010111 %
1!
#426
0!
#427
b110100111 )
b101010010 ,
b10101110 +
b10101110 $
b10101110 '
b10101110 %
1!
#428
0!
#429
b111111001 )
b110100100 ,
b1011100 +
b1011100 $
b1011100 '
b101011100 %
1!
#430
0!
#431
b110011100 )
b101000111 ,
b10111001 +
b10111001 $
b10111001 '
b10111001 %
1!
#432
0!
#433
b111100010 )
b110001101 ,
b1110011 +
b1110011 $
b1110011 '
b101110011 %
1!
#434
0!
#435
b101101110 )
b100011001 ,
b11100111 +
b11100111 $
b11100111 '
b11100111 %
1!
#436
0!
#437
b110000110 )
b100110001 ,
b11001111 +
b11001111 $
b11001111 '
b111001111 %
1!
#438
0!
#439
b110110110 )
b101100001 ,
b10011111 +
b10011111 $
b10011111 '
b110011111 %
1!
#440
0!
#441
1&
b10111 )
b111000010 ,
b111110 +
b111110 $
b111110 '
b100111110 %
1!
#442
0!
#443
0&
b111011001 )
b110000100 ,
b1111100 +
b1111100 $
b1111100 '
b1111100 %
1!
#444
0!
#445
b101011101 )
b100001000 ,
b11111000 +
b11111000 $
b11111000 '
b11111000 %
1!
#446
0!
#447
b101100100 )
b100001111 ,
b11110001 +
b11110001 $
b11110001 '
b111110001 %
1!
#448
0!
#449
b101110011 )
b100011110 ,
b11100010 +
b11100010 $
b11100010 '
b111100010 %
1!
#450
0!
#451
b110010000 )
b100111011 ,
b11000101 +
b11000101 $
b11000101 '
b111000101 %
1!
#452
0!
#453
b111001011 )
b101110110 ,
b10001010 +
b10001010 $
b10001010 '
b110001010 %
1!
#454
0!
#455
1&
b1000000 )
b111101011 ,
b10101 +
b10101 $
b10101 '
b100010101 %
1!
#456
0!
#457
b101011 )
b111010110 ,
b101010 +
b101010 $
b101010 '
b101010 %
1!
#458
0!
#459
b0 )
b110101011 ,
b1010101 +
b1010101 $
b1010101 '
b1010101 %
1!
#460
0!
#461
0&
b110101011 )
b101010110 ,
b10101010 +
b10101010 $
b10101010 '
b10101010 %
1!
#462
0!
#463
1&
b1 )
b110101100 ,
b1010100 +
b1010100 $
b1010100 '
b101010100 %
1!
#464
0!
#465
0&
b110101101 )
b101011000 ,
b10101000 +
b10101000 $
b10101000 '
b10101000 %
1!
#466
0!
#467
1&
b101 )
b110110000 ,
b1010000 +
b1010000 $
b1010000 '
b101010000 %
1!
#468
0!
#469
0&
b110110101 )
b101100000 ,
b10100000 +
b10100000 $
b10100000 '
b10100000 %
1!
#470
0!
#471
1&
b10100 )
b110111111 ,
b1000001 +
b1000001 $
b1000001 '
b101000001 %
1!
#472
0!
#473
0&
b111010010 )
b101111101 ,
b10000011 +
b10000011 $
b10000011 '
b10000011 %
1!
#474
0!
#475
1&
b1001111 )
b111111010 ,
b110 +
b110 $
b110 '
b100000110 %
1!
#476
0!
#477
b1001000 )
b111110011 ,
b1101 +
b1101 $
b1101 '
b1101 %
1!
#478
0!
#479
b111011 )
b111100110 ,
b11010 +
b11010 $
b11010 '
b11010 %
1!
#480
0!
#481
b100000 )
b111001011 ,
b110101 +
b110101 $
b110101 '
b110101 %
1!
#482
0!
#483
0&
b111101010 )
b110010101 ,
b1101011 +
b1101011 $
b1101011 '
b1101011 %
1!
#484
0!
#485
b101111110 )
b100101001 ,
b11010111 +
b11010111 $
b11010111 '
b11010111 %
1!
#486
0!
#487
b110100110 )
b101010001 ,
b10101111 +
b10101111 $
b10101111 '
b110101111 %
1!
#488
0!
#489
b111110111 )
b110100010 ,
b1011110 +
b1011110 $
b1011110 '
b101011110 %
1!
#490
0!
#491
b110011000 )
b101000011 ,
b10111101 +
b10111101 $
b10111101 '
b10111101 %
1!
#492
0!
#493
b111011010 )
b110000101 ,
b1111011 +
b1111011 $
b1111011 '
b101111011 %
1!
#494
0!
